bctone/__init__.py
bctone/client.py
bctone-0.1.0.dist-info/licenses/LICENSE
bctone-0.1.0.dist-info/METADATA
bctone-0.1.0.dist-info/WHEEL
bctone-0.1.0.dist-info/top_level.txt
bctone-0.1.0.dist-info/RECORD
