Metadata-Version: 2.4
Name: bctone
Version: 0.1.0
Summary: bctone SDK for RAG SaaS
Author-email: Damien Park <damien.bctone@gmail.com>
License: MIT
Requires-Python: >=3.9
License-File: LICENSE
Dynamic: license-file
